xnoted/__about__.py
xnoted/__init__.py
xnoted/app.py
xnoted/entry_points.py
xnoted/components/__init__.py
xnoted/components/body.py
xnoted/components/content.py
xnoted/components/createProjectForm.py
xnoted/components/footer.py
xnoted/components/footerLabel.py
xnoted/components/footerSearch.py
xnoted/components/importExportProject.py
xnoted/components/projects.py
xnoted/components/sidebar.py
xnoted/components/taskContainer.py
xnoted/components/taskHeader.py
xnoted/components/tasks.py
xnoted/screens/confirm.py
xnoted/screens/createProject.py
xnoted/screens/createTask.py
xnoted/screens/importExportProject.py
xnoted/screens/projects.py
xnoted/screens/selectProjects.py
xnoted/styles/main.tcss
xnoted/utils/__init__.py
xnoted/utils/constants.py
xnoted/utils/database.py
xnoted/utils/helpers.py
xnoted/README.md
xnoted-0.1.6.dist-info/METADATA
xnoted-0.1.6.dist-info/WHEEL
xnoted-0.1.6.dist-info/entry_points.txt
xnoted-0.1.6.dist-info/licenses/LICENSE.txt
xnoted-0.1.6.dist-info/RECORD
