Metadata-Version: 2.4
Name: xnoted
Version: 0.1.6
Summary: A powerful terminal-based task and note management application built with Python and Textual. Organize your tasks and notes into projects with a modern, keyboard-driven interface.
Project-URL: Documentation, https://github.com/babucarr32/xnoted#readme
Project-URL: Issues, https://github.com/babucarr32/xnoted/issues
Project-URL: Source, https://github.com/babucarr32/xnoted
Author-email: babucar32 <baboucarry@gmail.com>
License-Expression: MIT
License-File: LICENSE.txt
Classifier: Development Status :: 4 - Beta
Classifier: Programming Language :: Python
Classifier: Programming Language :: Python :: 3.8
Classifier: Programming Language :: Python :: 3.9
Classifier: Programming Language :: Python :: 3.10
Classifier: Programming Language :: Python :: 3.11
Classifier: Programming Language :: Python :: 3.12
Classifier: Programming Language :: Python :: Implementation :: CPython
Classifier: Programming Language :: Python :: Implementation :: PyPy
Requires-Python: >=3.11
Requires-Dist: platformdirs
Requires-Dist: textual>=6.6.0
